README.rst
setup.py
cufon/__init__.py
cufon/models.py
django_cufon.egg-info/PKG-INFO
django_cufon.egg-info/SOURCES.txt
django_cufon.egg-info/dependency_links.txt
django_cufon.egg-info/not-zip-safe
django_cufon.egg-info/top_level.txt