Metadata-Version: 1.0
Name: django-cufon
Version: 0.1.0
Summary: Cufon made easy in Django
Home-page: https://github.com/JonnyFunFun/django-cufon
Author: Jonathan Enzinna
Author-email: jonnyfunfun@gmail.com
License: GPLv3
Keywords: cufon,django
Platform: UNKNOWN
Classifier: Development Status :: 4 - Beta                 
Classifier: Environment :: Web Environment
Classifier: Framework :: Django
Classifier: Intended Audience :: Developers
Classifier: License :: OSI Approved :: GNU General Public License (GPL)
Classifier: Natural Language :: English
Classifier: Operating System :: OS Independent
Classifier: Programming Language :: Python :: 2.6
Classifier: Programming Language :: Python :: 2.7
Classifier: Topic :: Utilities
